{
  "insights": {
    "Poco Tráfico": {
      "reddit_voice": "Necesito ayuda con poco tráfico",
      "signal_count": 0
    },
    "Técnico": {
      "reddit_voice": "Necesito ayuda con técnico",
      "signal_count": 0
    },
    "Competencia": {
      "reddit_voice": "Necesito ayuda con competencia",
      "signal_count": 0
    },
    "Baja Conversión": {
      "reddit_voice": "Necesito ayuda con baja conversión",
      "signal_count": 0
    }
  },
  "metadata": {
    "generated_at": "2026-02-09T04:09:51.463285",
    "total_signals": 0,
    "version": "2.0-auto"
  }
}